simplify5d/__init__.py
simplify5d/simplify5d.py
simplify5d-0.2.4.dist-info/LICENSE
simplify5d-0.2.4.dist-info/METADATA
simplify5d-0.2.4.dist-info/WHEEL
simplify5d-0.2.4.dist-info/top_level.txt
simplify5d-0.2.4.dist-info/RECORD
