Metadata-Version: 2.1
Name: simplify5d
Version: 0.2.4
Summary: A module for simplifying 2D and 3D lines using Ramer-Douglas-Peucker algorithm
Home-page: https://github.com/jamescarruthers/simplify5d
Author: James Carruthers
Author-email: your.email@example.com
Classifier: Programming Language :: Python :: 3
Classifier: License :: OSI Approved :: MIT License
Classifier: Operating System :: OS Independent
Requires-Python: >=3.6
License-File: LICENSE
Requires-Dist: numpy
